{
  "project_info": {
    "project_number": "784739381492",
    "firebase_url": "https://paymentpc-4e0a9.firebaseio.com",
    "project_id": "paymentpc-4e0a9",
    "storage_bucket": "paymentpc-4e0a9.appspot.com"
  },
  "client": [
    {
      "client_info": {
        "mobilesdk_app_id": "1:784739381492:android:be032e91b238e09bc92ea1",
        "android_client_info": {
          "package_name": "com.example.payment_manage"
        }
      },
      "oauth_client": [
        {
          "client_id": "784739381492-7rn94derfim71b6cngelkgg3mordb15u.apps.googleusercontent.com",
          "client_type": 1,
          "android_info": {
            "package_name": "com.example.payment_manage",
            "certificate_hash": "fa22b40e7a0e81e3af355164cfb64a6d026ceb27"
          }
        },
        {
          "client_id": "784739381492-am3d73cqovhf27vkg3gaqiaem2csv6nt.apps.googleusercontent.com",
          "client_type": 3
        }
      ],
      "api_key": [
        {
          "current_key": "AIzaSyCslOwvLBFQQfZ9OZk_tzFlpBQ3HLxinP0"
        }
      ],
      "services": {
        "appinvite_service": {
          "other_platform_oauth_client": [
            {
              "client_id": "784739381492-am3d73cqovhf27vkg3gaqiaem2csv6nt.apps.googleusercontent.com",
              "client_type": 3
            }
          ]
        }
      }
    },
    {
      "client_info": {
        "mobilesdk_app_id": "1:784739381492:android:19b3248b090a2c14c92ea1",
        "android_client_info": {
          "package_name": "com.example.pcstore"
        }
      },
      "oauth_client": [
        {
          "client_id": "784739381492-2n4s327bojf404fh9k1d3angrn6rtdv2.apps.googleusercontent.com",
          "client_type": 1,
          "android_info": {
            "package_name": "com.example.pcstore",
            "certificate_hash": "fa22b40e7a0e81e3af355164cfb64a6d026ceb27"
          }
        },
        {
          "client_id": "784739381492-am3d73cqovhf27vkg3gaqiaem2csv6nt.apps.googleusercontent.com",
          "client_type": 3
        }
      ],
      "api_key": [
        {
          "current_key": "AIzaSyCslOwvLBFQQfZ9OZk_tzFlpBQ3HLxinP0"
        }
      ],
      "services": {
        "appinvite_service": {
          "other_platform_oauth_client": [
            {
              "client_id": "784739381492-am3d73cqovhf27vkg3gaqiaem2csv6nt.apps.googleusercontent.com",
              "client_type": 3
            }
          ]
        }
      }
    },
    {
      "client_info": {
        "mobilesdk_app_id": "1:784739381492:android:a2d75434c22f3b32c92ea1",
        "android_client_info": {
          "package_name": "com.short.company"
        }
      },
      "oauth_client": [
        {
          "client_id": "784739381492-am3d73cqovhf27vkg3gaqiaem2csv6nt.apps.googleusercontent.com",
          "client_type": 3
        }
      ],
      "api_key": [
        {
          "current_key": "AIzaSyCslOwvLBFQQfZ9OZk_tzFlpBQ3HLxinP0"
        }
      ],
      "services": {
        "appinvite_service": {
          "other_platform_oauth_client": [
            {
              "client_id": "784739381492-am3d73cqovhf27vkg3gaqiaem2csv6nt.apps.googleusercontent.com",
              "client_type": 3
            }
          ]
        }
      }
    }
  ],
  "configuration_version": "1"
}